{
  "dt.in.th": {
    "blurhash": "v384ucyY9F-V#6RitSV[00sjxZE3OrxtnORoH;S3pIxZuPtlIAn%00RO%MRl",
    "description": "Thai Pangsakulyanont’s web site",
    "backlink": {
      "rect": null,
      "href": "https://webring.wonderful.software#dt.in.th"
    },
    "mobileImageUrlV2": "https://wonderfulsoftware.github.io/webring-site-screenshots/dt.in.th_375w@2x.png",
    "lastUpdated": "2023-04-27T00:57:49.285Z",
    "url": "https://dt.in.th",
    "screenshotUpdatedAt": "2022-04-04T00:57:27.370Z",
    "number": 1
  },
  "wonderful.software": {
    "blurhash": "v7S$fXRP?^tQDOofx]ayn4kCR*V@%~R*DiaeTwjFMdkCELVsentlVsMeR*yC",
    "description": "a website about software engineering",
    "backlink": {
      "rect": null,
      "href": "https://webring.wonderful.software#wonderful.software"
    },
    "mobileImageUrlV2": "https://wonderfulsoftware.github.io/webring-site-screenshots/wonderful.software_375w@2x.png",
    "screenshotUpdatedAt": "2022-01-30T14:12:35.617Z",
    "lastUpdated": "2023-04-27T00:57:36.484Z",
    "url": "https://wonderful.software",
    "number": 0
  },
  "notaboutcode.com": {
    "blurhash": "vVQmCrWX%MWBIUkCofay~qWBRjoe_3aeRjoLRjofofWC4noft7WBIUbIj[oL",
    "description": "Hugo theme even example site.",
    "backlink": {
      "rect": null,
      "href": "https://webring.wonderful.software#notaboutcode.com"
    },
    "mobileImageUrlV2": "https://wonderfulsoftware.github.io/webring-site-screenshots/notaboutcode.com_375w@2x.png",
    "screenshotUpdatedAt": "2022-02-20T00:51:21.929Z",
    "lastUpdated": "2023-04-27T00:58:07.231Z",
    "url": "http://www.notaboutcode.com",
    "number": 2
  },
  "monosor.dev": {
    "blurhash": "v4S?DV8_xt%M~WWAE1WCEMbvocniE1R,t7s:=|slWWkWi{xHt7ozInInV[oL",
    "description": null,
    "backlink": {
      "rect": "283:40:-284:440",
      "href": "https://webring.wonderful.software/#monosor.dev"
    },
    "mobileImageUrlV2": "https://wonderfulsoftware.github.io/webring-site-screenshots/monosor.dev_375w@2x.png",
    "screenshotUpdatedAt": "2022-10-13T11:51:33.610Z",
    "lastUpdated": "2022-10-13T11:51:33.610Z",
    "url": "https://monosor.dev"
  },
  "monosor.com": {
    "blurhash": "v39?tN}@0#E2%MFeEMwI;fNGE#t7[oV?F1t7,;$jX8Nct7t7W=R*EMR*s:of",
    "description": "narze's digital garden",
    "backlink": {
      "rect": "32:21:171.5:207",
      "href": "https://webring.wonderful.software#monosor.com"
    },
    "mobileImageUrlV2": "https://wonderfulsoftware.github.io/webring-site-screenshots/monosor.com_375w@2x.png",
    "screenshotUpdatedAt": "2021-11-15T17:21:16.447Z",
    "lastUpdated": "2022-03-03T00:53:35.202Z",
    "url": "https://monosor.com"
  },
  "chrisza.me": {
    "blurhash": "v7Q][|00%2oJ00Rit8xv00yDoz-;00-oD%IU00xaMxIU0c_N-;R*00%MxuWV",
    "description": "A blog of Chris, a human who love to learn more about himself and the world",
    "backlink": {
      "rect": "24:32:291:14",
      "href": "https://webring.wonderful.software#chrisza.me"
    },
    "mobileImageUrlV2": "https://wonderfulsoftware.github.io/webring-site-screenshots/chrisza.me_375w@2x.png",
    "lastUpdated": "2023-04-27T00:58:51.480Z",
    "url": "https://chrisza.me",
    "screenshotUpdatedAt": "2023-04-11T00:56:00.663Z",
    "number": 5
  },
  "srakrn.me": {
    "blurhash": "v7R:KS9H?bt7p2IXIVxu~SIW9bxaRME2WZbIIvIpoJa$4?bIoJt79GWBWEt6",
    "description": "Data Engineer and BI Developer at Adastra Thailand. Distinctions include ETL workflow, Data Warehousing, BI, Data Science, ML, and more.",
    "backlink": {
      "rect": null,
      "href": "https://webring.wonderful.software/#srakrn.me"
    },
    "mobileImageUrlV2": "https://wonderfulsoftware.github.io/webring-site-screenshots/srakrn.me_375w@2x.png",
    "lastUpdated": "2023-04-27T00:59:06.663Z",
    "url": "https://srakrn.me",
    "screenshotUpdatedAt": "2022-05-26T01:12:09.920Z",
    "number": 7
  },
  "unnawut.com": {
    "blurhash": "v6S$ovD%~q%M?bj[IUj[xua#RjoJofoej@WCt8fkWBofocofofWBR*ogogWA",
    "description": null,
    "backlink": {
      "rect": "12:17:160:1101.3125",
      "href": "https://webring.wonderful.software#unnawut.com"
    },
    "mobileImageUrlV2": "https://wonderfulsoftware.github.io/webring-site-screenshots/unnawut.com_375w@2x.png",
    "lastUpdated": "2023-04-27T00:58:56.865Z",
    "url": "http://www.unnawut.com",
    "screenshotUpdatedAt": "2021-10-05T17:18:53.805Z",
    "number": 6
  },
  "serial-coder.com": {
    "blurhash": "vKS6PlWB~qofIUayxuj[?bae9Fj[%MWBD%ofD%ayxuj[9Fay-;jtD%WBxuj[",
    "description": "When coding is life... - Serial Coder",
    "backlink": null,
    "mobileImageUrlV2": "https://wonderfulsoftware.github.io/webring-site-screenshots/serial-coder.com_375w@2x.png",
    "screenshotUpdatedAt": "2021-11-08T17:21:57.041Z",
    "lastUpdated": "2021-11-10T17:14:25.171Z",
    "url": "https://www.serial-coder.com"
  },
  "ggolfz.codes": {
    "blurhash": "v.MQ*Jj[xuj[IUWBofay~qj[Rjj[-;WBayayIUj[j[j[xuayfQayM{j[j[j[",
    "description": "GGolfz",
    "backlink": {
      "rect": "20:20:22.125:580",
      "href": "https://webring.wonderful.software#ggolfz.me"
    },
    "mobileImageUrlV2": "https://wonderfulsoftware.github.io/webring-site-screenshots/ggolfz.codes_375w@2x.png",
    "lastUpdated": "2022-01-27T17:17:40.451Z",
    "url": "https://ggolfz.me",
    "screenshotUpdatedAt": "2022-01-25T17:18:33.904Z"
  },
  "knowlats.dev": {
    "blurhash": "v4RMe?00-;-;~q-qRPoLaexaV@oft7ofRPof4nNFofWBx]tRNGM{_3xuD%bI",
    "description": "Share everything about backend web development. Coding in JavaScript and Java.",
    "backlink": {
      "rect": null,
      "href": "https://webring.wonderful.software#knowlats.dev"
    },
    "mobileImageUrlV2": "https://wonderfulsoftware.github.io/webring-site-screenshots/knowlats.dev_375w@2x.png",
    "screenshotUpdatedAt": "2023-03-31T01:00:23.833Z",
    "lastUpdated": "2023-04-27T00:59:32.758Z",
    "url": "https://knowlats.dev",
    "number": 9
  },
  "petepittawat.dev": {
    "blurhash": "vyOWyyM|xufkW=bIRkay~qR*Rjf6xuayWCj[9Foet6ayWAocoej[%Ls.oJf6",
    "description": "Where Technology Can Enhance Our Lives.",
    "backlink": {
      "rect": "32:32:171.5:40292.34375",
      "href": "https://webring.wonderful.software#petepittawat.dev"
    },
    "mobileImageUrlV2": "https://wonderfulsoftware.github.io/webring-site-screenshots/petepittawat.dev_375w@2x.png",
    "lastUpdated": "2023-04-27T00:59:38.769Z",
    "url": "https://petepittawat.dev",
    "screenshotUpdatedAt": "2023-04-25T00:58:07.100Z",
    "number": 10
  },
  "rayriffy.com": {
    "blurhash": "vVE:Y;m*s,s8A2ngnOjZ^*tlWXW=4Tb^T1ay~2SikDbIrmn%jEkD.7r=nhjY",
    "description": "The front frontier of rayriffy.com!",
    "backlink": {
      "rect": null,
      "href": "https://webring.wonderful.software#rayriffy.com"
    },
    "mobileImageUrlV2": "https://wonderfulsoftware.github.io/webring-site-screenshots/rayriffy.com_375w@2x.png",
    "screenshotUpdatedAt": "2023-03-18T01:01:23.552Z",
    "lastUpdated": "2023-04-27T01:00:00.905Z",
    "url": "https://rayriffy.com",
    "number": 12
  },
  "kusumotolab.com": {
    "blurhash": "vAOzPl9Yt8t700R$RjoL00WURjj[4-xbWAWB_M$,oxW;?vxIt7NG-;ogoffj",
    "description": "ความรู้ ความสุข ความเศร้า ความทรงจำ",
    "backlink": {
      "rect": "32:32:176.5:9112.21875",
      "href": "https://webring.wonderful.software#kusumotolab.com"
    },
    "mobileImageUrlV2": "https://wonderfulsoftware.github.io/webring-site-screenshots/kusumotolab.com_375w@2x.png",
    "screenshotUpdatedAt": "2023-04-26T00:57:55.897Z",
    "lastUpdated": "2023-04-27T01:00:11.992Z",
    "url": "https://kusumotolab.com",
    "number": 13
  },
  "neizod.dev": {
    "blurhash": "v6SigPRP_NkCV?t8%Nof?bozWCaet5WBWrWX?GaeozozIUbIt7ax4oozxaay",
    "description": "insufficient data for meaningful answer",
    "backlink": {
      "rect": "40:40:331:4",
      "href": "https://webring.wonderful.software#neizod.dev"
    },
    "mobileImageUrlV2": "https://wonderfulsoftware.github.io/webring-site-screenshots/neizod.dev_375w@2x.png",
    "lastUpdated": "2023-04-27T01:00:18.642Z",
    "url": "https://neizod.dev",
    "screenshotUpdatedAt": "2023-03-15T01:03:04.249Z",
    "number": 14
  },
  "wiput.me": {
    "blurhash": "v4TI,at7%Mt7WBoffQj[~qofIUoft7ofRjj[00ofxufQM{j[t7j[?bj[IUof",
    "description": "I am Software Engineer...",
    "backlink": {
      "rect": "32:32:327:16",
      "href": "https://webring.wonderful.software#wiput.me"
    },
    "mobileImageUrlV2": "https://wonderfulsoftware.github.io/webring-site-screenshots/wiput.me_375w@2x.png",
    "screenshotUpdatedAt": "2023-01-03T01:01:15.901Z",
    "lastUpdated": "2023-04-27T01:00:23.486Z",
    "url": "https://wiput.me",
    "number": 15
  },
  "jojoee.com": {
    "blurhash": "v3SijY00N3IX.9XBIvNL%zx]IUIV~p~W-:%K4mVq^*?F_0s$s6-mD~xon#V?",
    "description": null,
    "backlink": {
      "rect": "32:19:15:6227.375",
      "href": "https://webring.wonderful.software/#/jojoee.com"
    },
    "mobileImageUrlV2": "https://wonderfulsoftware.github.io/webring-site-screenshots/jojoee.com_375w@2x.png",
    "screenshotUpdatedAt": "2022-05-25T01:08:49.082Z",
    "lastUpdated": "2023-04-27T00:59:45.572Z",
    "url": "https://jojoee.com",
    "number": 11
  },
  "saltyaom.com": {
    "blurhash": "v4TI,axu~qWBt7WBt7fQ%MofD%j[t7ayfQWB%MayIUt7xuayRjWBWBayofof",
    "description": "悪い人でよかった",
    "backlink": null,
    "mobileImageUrlV2": "https://wonderfulsoftware.github.io/webring-site-screenshots/saltyaom.com_375w@2x.png",
    "lastUpdated": "2021-11-10T17:16:03.289Z",
    "url": "https://saltyaom.com",
    "screenshotUpdatedAt": "2021-07-31T17:21:32.625Z"
  },
  "icez.net": {
    "mobileImageUrlV2": "https://wonderfulsoftware.github.io/webring-site-screenshots/icez.net_375w@2x.png",
    "blurhash": "v1RV^L00000000t,rXt700.St7NG00f+E1Na00o}$Pt700^+TJkW00~q-;xu",
    "screenshotUpdatedAt": "2022-12-27T00:59:53.173Z",
    "description": null,
    "backlink": {
      "rect": "32:18:787:3008",
      "href": "https://webring.wonderful.software/#icez.net"
    },
    "lastUpdated": "2023-04-27T01:00:49.199Z",
    "url": "https://icez.net",
    "number": 17
  },
  "kykungz.dev": {
    "mobileImageUrlV2": "https://wonderfulsoftware.github.io/webring-site-screenshots/kykungz.dev_375w@2x.png",
    "blurhash": "viNd{:oJ.8jb7MWBIUoftnayRjj[vhofxvay~BWWRjof$vkCRjWVR4j[kBf7",
    "screenshotUpdatedAt": "2022-01-29T17:22:37.821Z",
    "description": "Personal website of Kongpon Charanwattanakit",
    "backlink": {
      "rect": null,
      "href": "https://webring.wonderful.software#kykungz.dev"
    },
    "lastUpdated": "2023-04-27T01:01:03.394Z",
    "url": "https://kykungz.dev",
    "number": 18
  },
  "jittagornp.me": {
    "mobileImageUrlV2": "https://wonderfulsoftware.github.io/webring-site-screenshots/jittagornp.me_375w@2x.png",
    "blurhash": "vFP?wB;4?HOX4:OmIojH4:pHIVnk00$j%2S200t7oej[00nQxuX6?^ACIUwy",
    "screenshotUpdatedAt": "2023-04-27T01:01:14.911Z",
    "description": "โดย จิตกร พิทักษ์เมธากุล",
    "backlink": {
      "rect": "30:30:281:13",
      "href": "https://webring.wonderful.software/#/jittagornp.me"
    },
    "lastUpdated": "2023-04-27T01:01:14.911Z",
    "url": "https://www.jittagornp.me",
    "number": 19
  },
  "pandora.sh": {
    "mobileImageUrlV2": "https://wonderfulsoftware.github.io/webring-site-screenshots/pandora.sh_375w@2x.png",
    "blurhash": "v37-c-~q9FWB?bxuRjM{00IU%MM{00M{xuayM{s:ogof_3RjIUofIoM{t7ay",
    "screenshotUpdatedAt": "2022-03-12T00:52:07.719Z",
    "description": null,
    "backlink": {
      "rect": "20:20:177.5:2429",
      "href": "https://webring.wonderful.software#pandora.sh"
    },
    "lastUpdated": "2023-04-27T01:01:42.636Z",
    "url": "https://pandora.sh",
    "number": 20
  },
  "warat.win": {
    "url": "https://warat.win",
    "mobileImageUrlV2": "https://wonderfulsoftware.github.io/webring-site-screenshots/warat.win_375w@2x.png",
    "blurhash": "vB7BDyf4IAWFD+j;t7bJ9GoHxukD_4awM{WYxvjqRjWYD*oIt6kDohawxua~",
    "screenshotUpdatedAt": "2023-02-14T01:05:38.765Z",
    "description": "Full-stack Software Engineer based in Bangkok, Thailand.",
    "backlink": {
      "rect": "24:24:175.5:10076.140625",
      "href": "https://webring.wonderful.software#warat.win"
    },
    "lastUpdated": "2023-04-27T01:01:52.050Z",
    "number": 21
  },
  "poolsawat.com": {
    "url": "https://www.poolsawat.com",
    "mobileImageUrlV2": "https://wonderfulsoftware.github.io/webring-site-screenshots/poolsawat.com_375w@2x.png",
    "blurhash": "vFR:QjRj-nof^vofoMjt5Fogs+fQ-lRjWCj[s+ayR+ayR=ofRjj[~NfPIqfk",
    "screenshotUpdatedAt": "2023-04-27T01:09:45.028Z",
    "description": "\"In the end we only regret The changes we didn't take.\" เพราะสุดท้ายแล้ว เรามักเสียใจกับสิ่งที่ไม่ได้ทำ มากกว่า...สิ่งที่ได้ทำลงไป",
    "backlink": {
      "rect": "32:25:171.5:14283.15625",
      "href": "https://webring.wonderful.software#poolsawat.com"
    },
    "lastUpdated": "2023-04-27T01:09:45.028Z",
    "number": 51
  },
  "mymintrabbit.com": {
    "url": "http://www.mymintrabbit.com",
    "mobileImageUrlV2": "https://wonderfulsoftware.github.io/webring-site-screenshots/mymintrabbit.com_375w@2x.png",
    "blurhash": "vYLE]XWB~Tj[?gaeE9j[SvayWCj[NOafn#j[%Naxadj[-nayWEj[acayozj[",
    "screenshotUpdatedAt": "2021-11-10T17:18:03.822Z",
    "description": null,
    "backlink": null,
    "lastUpdated": "2021-11-10T17:18:03.822Z"
  },
  "savepong.com": {
    "url": "https://www.savepong.com",
    "mobileImageUrlV2": "https://wonderfulsoftware.github.io/webring-site-screenshots/savepong.com_375w@2x.png",
    "blurhash": "v6OgKPof00of00ayW@ay00ay?vj[00ay_Nj[00fQ^+fQD4j[v~ayQlj[VXay",
    "screenshotUpdatedAt": "2022-10-07T01:43:28.105Z",
    "description": "savepong.com is your first and best source for all of the information you’re looking for. From general topics to more of what you would expect to find here, savepong.com has it all. We hope you find what you are searching for!",
    "backlink": null,
    "lastUpdated": "2022-10-07T01:43:28.105Z"
  },
  "shayennn.com": {
    "url": "https://shayennn.com",
    "mobileImageUrlV2": "https://wonderfulsoftware.github.io/webring-site-screenshots/shayennn.com_375w@2x.png",
    "blurhash": "vhJH%MjZWBWV00ofR*WV~qj[oLjZoyfkoLn%9Ffkj[jZ%MjskCWVs:ofWWWp",
    "screenshotUpdatedAt": "2023-02-20T01:09:51.537Z",
    "description": null,
    "backlink": {
      "rect": "32:21:171.5:284.6875",
      "href": "https://webring.wonderful.software#phitchaw.at"
    },
    "lastUpdated": "2023-04-23T01:07:42.141Z"
  },
  "mahasak.com": {
    "url": "https://mahasak.com",
    "mobileImageUrlV2": "https://wonderfulsoftware.github.io/webring-site-screenshots/mahasak.com_375w@2x.png",
    "blurhash": "vFONB[IUWAax00t7WBfk00j[WBj[RjkCWBj[~qV@WBWB_4j]xufk-;j[t7ay",
    "screenshotUpdatedAt": "2021-08-10T17:22:46.810Z",
    "description": null,
    "backlink": null,
    "lastUpdated": "2021-11-10T17:16:12.447Z"
  },
  "jitrak.dev": {
    "url": "https://jitrak.dev",
    "mobileImageUrlV2": "https://wonderfulsoftware.github.io/webring-site-screenshots/jitrak.dev_375w@2x.png",
    "blurhash": "v88z=PNG0Jxu~pIT9F%2x^IUM{xvRjj@t7RjnN%M%MMx00s;-;NG00so-;W.",
    "screenshotUpdatedAt": "2021-07-12T17:27:34.084Z",
    "description": "A story about Jitrak development.",
    "backlink": {
      "rect": "32:68:21:224",
      "href": "https://webring.wonderful.software#jitrak.dev"
    },
    "lastUpdated": "2023-04-24T01:03:24.867Z"
  },
  "www.varokas.com": {
    "url": "https://www.varokas.com",
    "mobileImageUrlV2": "https://wonderfulsoftware.github.io/webring-site-screenshots/www.varokas.com_375w@2x.png",
    "blurhash": "vBRp8,WaV@xu_NRiozae_4R$s;Wn9YogWBjuX4n+baWCIAtQV@bI%gaLt7WB",
    "screenshotUpdatedAt": "2023-02-21T01:09:30.832Z",
    "description": null,
    "backlink": null,
    "lastUpdated": "2023-04-24T01:03:48.346Z"
  },
  "somkiat.cc": {
    "url": "https://www.somkiat.cc",
    "mobileImageUrlV2": "https://wonderfulsoftware.github.io/webring-site-screenshots/somkiat.cc_375w@2x.png",
    "blurhash": "v5Q9~0ImxaZ$4nE2t5%0=Y?FozK503w%IvNL9X9t$~#lyqy6oG$d~C$kWZJo",
    "screenshotUpdatedAt": "2023-04-24T01:03:39.258Z",
    "description": null,
    "backlink": {
      "rect": "32:14:230.5:42",
      "href": "https://webring.wonderful.software#somkiat.cc"
    },
    "lastUpdated": "2023-04-24T01:03:39.258Z"
  },
  "doopdip.me": {
    "url": "https://doopdip.me",
    "mobileImageUrlV2": "https://wonderfulsoftware.github.io/webring-site-screenshots/doopdip.me_375w@2x.png",
    "blurhash": "vOR:HGWB~qj[4nof_3ay9FWB%Mj[xuofWBay%MWBM{j[-;ofIUWB-;ayM{j[",
    "screenshotUpdatedAt": "2022-07-27T01:23:08.037Z",
    "description": "เลาเดฟบ้าน ๆ เลาเดฟเลี้ยงวัว ~",
    "backlink": {
      "rect": "40:44:167.5:321",
      "href": "https://webring.wonderful.software#doopdip.me"
    },
    "lastUpdated": "2023-04-23T01:08:24.978Z"
  },
  "dont.works": {
    "url": "https://dont.works",
    "mobileImageUrlV2": "https://wonderfulsoftware.github.io/webring-site-screenshots/dont.works_375w@2x.png",
    "blurhash": "vpNKI-fk-;j?~qayM{j[xuayWBbH%Mj[RjWCIUfkofayt7WBj[j[V@ayj[j[",
    "screenshotUpdatedAt": "2022-09-06T01:30:40.567Z",
    "description": "เบียร์ กาแฟ เนื้อ นอน",
    "backlink": {
      "rect": "32:32:89:19",
      "href": "https://webring.wonderful.software/#/dont.works"
    },
    "lastUpdated": "2023-04-27T01:00:38.959Z",
    "number": 16
  },
  "mikkipastel.com": {
    "url": "https://www.mikkipastel.com",
    "mobileImageUrlV2": "https://wonderfulsoftware.github.io/webring-site-screenshots/mikkipastel.com_375w@2x.png",
    "blurhash": "vQG*v%-iI-SzyWOFnjsm?v$MxaSO^lIqt7ni?HnTogSO?]S1M{oJ~VbbX8R-",
    "screenshotUpdatedAt": "2022-07-26T01:21:44.854Z",
    "description": "Android developer & Blogger.\nบล็อก Android, Chatbot, Programming, lifestyle, สรุป Event และ Online Course ต่างๆ",
    "backlink": {
      "rect": "28.80000114440918:27.60000228881836:20.475000381469727:53.04999923706055",
      "href": "https://webring.wonderful.software#mikkipastel.com"
    },
    "lastUpdated": "2023-04-23T01:08:40.188Z"
  },
  "ntsd.me": {
    "url": "https://ntsd.me",
    "mobileImageUrlV2": "https://wonderfulsoftware.github.io/webring-site-screenshots/ntsd.me_375w@2x.png",
    "blurhash": "v0TSUA-;fQ-;%MfQfQfQfQfQfQfQ%MfQfQfQfQfQfQfQ%MfQfQfQfQfQfQfQ",
    "screenshotUpdatedAt": "2021-03-13T17:37:48.925Z",
    "description": null,
    "backlink": null,
    "lastUpdated": "2022-01-27T17:22:16.840Z"
  },
  "pontakorn.dev": {
    "url": "https://pontakorn.dev",
    "mobileImageUrlV2": "https://wonderfulsoftware.github.io/webring-site-screenshots/pontakorn.dev_375w@2x.png",
    "blurhash": "v9SF;NR+~pj[WJWEobofRqkDRiWBx]RkM{fPk7WXjcoL--fkWFof_LayM|j[",
    "screenshotUpdatedAt": "2022-10-16T01:46:07.285Z",
    "description": null,
    "backlink": {
      "rect": "64:48:247.90625:16",
      "href": "https://webring.wonderful.software#pontakorn.dev"
    },
    "lastUpdated": "2023-04-23T01:08:52.574Z"
  },
  "wp.curve.in.th": {
    "url": "https://wp.curve.in.th/",
    "mobileImageUrlV2": "https://wonderfulsoftware.github.io/webring-site-screenshots/wp.curve.in.th_375w@2x.png",
    "blurhash": "voMj,YRP?bt8Ipt7IURjofV@RikB_3ofxvWB~qWBjZs:xuj[WBWBWBfkR*ax",
    "screenshotUpdatedAt": "2022-08-29T01:30:26.543Z",
    "description": "An experienced web developer // Now, I’m doing reasearch in NLP, Transfer Learning, and Continual Learning interested on how to leverage linguistic knowledge to improve trasferablity in cross-lingual models",
    "backlink": {
      "rect": "360:32:7.5:60.5",
      "href": "https://webring.wonderful.software#wp.curve.in.th"
    },
    "lastUpdated": "2023-04-23T01:09:04.030Z"
  },
  "adamblog.co": {
    "url": "https://adamblog.co",
    "mobileImageUrlV2": "https://wonderfulsoftware.github.io/webring-site-screenshots/adamblog.co_375w@2x.png",
    "blurhash": "v9S6GOHryCK5y;TeRQZ$mS#8tRXnyqX-enrXrEZ$R%S~u4b_V@rrv~r?oytR",
    "screenshotUpdatedAt": "2023-03-03T03:00:49.826Z",
    "description": "การเปลี่ยนแปลงที่แท้จริง คือการทำอย่างสม่ำเสมอ ต่อเนื่อง ในทุกๆ วัน",
    "backlink": {
      "rect": "24:28.765625:239.5:10.6171875",
      "href": "https://webring.wonderful.software#adamblog.co"
    },
    "lastUpdated": "2023-04-23T01:09:16.196Z"
  },
  "pat.chormai.org": {
    "url": "https://pat.chormai.org",
    "mobileImageUrlV2": "https://wonderfulsoftware.github.io/webring-site-screenshots/pat.chormai.org_375w@2x.png",
    "blurhash": "vSRfh3ax~qWCD%of-;WBt7ayRjfR%gayD%j@-;azIUoe%MayM{oeazayWAj[",
    "screenshotUpdatedAt": "2021-02-13T17:30:20.960Z",
    "description": "A PhD Candidate at Max Planck School of Cognition",
    "backlink": {
      "rect": "66:18:190.890625:3328.734375",
      "href": "https://webring.wonderful.software#pat.chormai.org"
    },
    "lastUpdated": "2023-04-24T01:05:00.539Z"
  },
  "curiousdev.in.th": {
    "url": "https://curiousdev.in.th",
    "mobileImageUrlV2": "https://wonderfulsoftware.github.io/webring-site-screenshots/curiousdev.in.th_375w@2x.png",
    "blurhash": "v1S$ov00?b%M009F%MD%9F?b_39F00t7_3Rj00Rj%MWB-;D%IU%M-;D%D%of",
    "screenshotUpdatedAt": "2021-01-21T15:00:47.046Z",
    "description": "Full-stack web developer who always curiosity and learn new things.",
    "backlink": {
      "rect": "32:61.1875:282.3125:47",
      "href": "https://webring.wonderful.software#curiousdev.in.th"
    },
    "lastUpdated": "2023-04-27T01:05:58.764Z",
    "number": 34
  },
  "heyfirst.co": {
    "url": "https://heyfirst.co",
    "mobileImageUrlV2": "https://wonderfulsoftware.github.io/webring-site-screenshots/heyfirst.co_375w@2x.png",
    "blurhash": "v3S$ov00-;WB00D%xuM{-;M{IUj@-;IUD%xaxut7WBWB%Mt7Mxay~p%MM{j[",
    "screenshotUpdatedAt": "2023-01-31T01:10:36.665Z",
    "description": "A Full-stack engineer, Building web-things at Unity Ads. Living in Helsinki, Finland.",
    "backlink": {
      "rect": "16:16:331:20",
      "href": "https://webring.wonderful.software#heyfirst.co"
    },
    "lastUpdated": "2023-04-27T01:06:07.776Z",
    "number": 35
  },
  "wiennat.com": {
    "url": "https://www.wiennat.com",
    "mobileImageUrlV2": "https://wonderfulsoftware.github.io/webring-site-screenshots/wiennat.com_375w@2x.png",
    "blurhash": "v@P6]gWBt7j[t7f6ayaz~qayRjj[M{fQj[ayD%a|kCj@t7fPayazt7j[ayfQ",
    "screenshotUpdatedAt": "2023-01-08T01:10:33.825Z",
    "description": "random rambling",
    "backlink": {
      "rect": "21:31:334.8125:3286.421875",
      "href": "https://webring.wonderful.software#wiennat.com"
    },
    "lastUpdated": "2023-04-25T01:04:52.408Z"
  },
  "llun.me": {
    "url": "https://www.llun.me",
    "mobileImageUrlV2": "https://wonderfulsoftware.github.io/webring-site-screenshots/llun.me_375w@2x.png",
    "blurhash": "v4SPb44n~V-:?FMxIpbcs8n#R*W=^*M{Ioxt%2WCM|WB?bM}M{WANexuxtRP",
    "screenshotUpdatedAt": "2023-03-26T01:09:52.166Z",
    "description": "Life, Ride and Code",
    "backlink": {
      "rect": "26:26:177.953125:76.625",
      "href": "https://webring.wonderful.software#llun.me"
    },
    "lastUpdated": "2023-04-27T01:06:32.137Z",
    "number": 37
  },
  "t6tg.com": {
    "url": "https://t6tg.com",
    "mobileImageUrlV2": "https://wonderfulsoftware.github.io/webring-site-screenshots/t6tg.com_375w@2x.png",
    "blurhash": "vtKKs]ayjOfQN5j[t8f6tKayofj[IWj[fgfj?KayRhj[WCj[W9azj[j[axay",
    "screenshotUpdatedAt": "2022-08-29T01:31:52.785Z",
    "description": "Thanawat Gulati • CSKMUNTB#32 | t6tg.com | Google Developer Student Clubs Lead | Microsoft Learn Student Ambassador (MLSA)",
    "backlink": {
      "rect": "44.72039794921875:44.72039794921875:213.13980102539062:349.6398010253906",
      "href": "https://webring.wonderful.software#t6tg.com"
    },
    "lastUpdated": "2023-04-26T01:04:40.107Z"
  },
  "thanapon.info": {
    "url": "https://thanapon.info",
    "mobileImageUrlV2": "https://wonderfulsoftware.github.io/webring-site-screenshots/thanapon.info_375w@2x.png",
    "blurhash": "v%N^e-ofRjV[9FayWBj[~qR*t7t7_3a|ofayogoeRjWBofafWCj[oLWBozof",
    "screenshotUpdatedAt": "2023-03-06T01:11:33.212Z",
    "description": "Blog April 27, 2020 Hello world! Welcome to WordPress. This is your first post. Edit or delete it, then start writing!",
    "backlink": {
      "rect": "75:62:300:60",
      "href": "https://webring.wonderful.software#thanapon.info"
    },
    "lastUpdated": "2023-04-27T01:06:56.885Z",
    "number": 39
  },
  "mr.touno.io": {
    "url": "https://mr.touno.io",
    "mobileImageUrlV2": "https://wonderfulsoftware.github.io/webring-site-screenshots/mr.touno.io_375w@2x.png",
    "blurhash": "v9Rfh44T$$s,9}JTtQxav*n4V[oz_N.8S$WY-WxDMyR+OZtlWUMx9Haen#Ri",
    "screenshotUpdatedAt": "2023-04-27T01:07:23.857Z",
    "description": "Hey there, My name is Kananek Thongkam and i'm a Full Stack Engineer specialist.",
    "backlink": {
      "rect": "60.796875:17:265.390625:6835.015625",
      "href": "https://webring.wonderful.software#mr.touno.io"
    },
    "lastUpdated": "2023-04-27T01:07:23.857Z",
    "number": 40
  },
  "suam.wtf": {
    "url": "https://suam.wtf",
    "mobileImageUrlV2": "https://wonderfulsoftware.github.io/webring-site-screenshots/suam.wtf_375w@2x.png",
    "blurhash": "v5S?DV9F-;-p~qxtD%RjIUt7ofRj%Mt7ayWB%MxuM{M{009ZxuxuWBWBM{j[",
    "screenshotUpdatedAt": "2023-03-25T01:04:42.964Z",
    "description": "A Hackers' Labyrinth",
    "backlink": {
      "rect": null,
      "href": "https://webring.wonderful.software#suam.wtf"
    },
    "lastUpdated": "2023-04-27T01:07:31.273Z",
    "number": 41
  },
  "blog.oatto.dev": {
    "url": "https://blog.oatto.dev",
    "mobileImageUrlV2": "https://wonderfulsoftware.github.io/webring-site-screenshots/blog.oatto.dev_375w@2x.png",
    "blurhash": "v7Ss88xa~qM{j]RiD%t7NGWBM{aya}f5Rjjta#oeazofWVofozofRjt7t7WB",
    "screenshotUpdatedAt": "2023-01-23T01:05:53.443Z",
    "description": "Welcome to very cool blog which you will find a lot of things here. Especially about programming and my life ;)\n",
    "backlink": {
      "rect": "32:24:103:105",
      "href": "https://webring.wonderful.software#blog.oatto.dev"
    },
    "lastUpdated": "2023-04-27T01:07:39.610Z",
    "number": 42
  },
  "toupawa.com": {
    "url": "https://toupawa.com",
    "mobileImageUrlV2": "https://wonderfulsoftware.github.io/webring-site-screenshots/toupawa.com_375w@2x.png",
    "blurhash": "vTG+RIoxV]WBNFRkbFof~qt6oMWB~WWBogofk8oNoeWB-;bXWCj]_3e?j?ay",
    "screenshotUpdatedAt": "2023-03-31T01:08:39.219Z",
    "description": "Toupawa Blog is a blog space for sharing an experience of software development.",
    "backlink": {
      "rect": "32:32:219:6273",
      "href": "https://webring.wonderful.software#toupawa.com"
    },
    "lastUpdated": "2023-04-27T01:07:57.231Z",
    "number": 43
  },
  "blog.karnwong.me": {
    "url": "https://blog.karnwong.me",
    "mobileImageUrlV2": "https://wonderfulsoftware.github.io/webring-site-screenshots/blog.karnwong.me_375w@2x.png",
    "blurhash": "v2S?DV9c?d.9~qs+ITjX%MV@Rixa%LWAWAt69FayxuWBM{Rjofxu9FWCkCWW",
    "screenshotUpdatedAt": "2021-08-28T17:26:21.248Z",
    "description": null,
    "backlink": {
      "rect": "32:22:172:24",
      "href": "https://webring.wonderful.software#blog.karnwong.me"
    },
    "lastUpdated": "2022-10-01T01:54:31.561Z"
  },
  "thiti.dev": {
    "url": "https://thiti.dev",
    "mobileImageUrlV2": "https://wonderfulsoftware.github.io/webring-site-screenshots/thiti.dev_375w@2x.png",
    "blurhash": "vbD9n@s.IUbI?bR*a#ayxvNHt8ae~qs.RPfR_3jYRjfltRNaozWB%Mj[oejZ",
    "screenshotUpdatedAt": "2023-04-26T10:01:25.451Z",
    "description": "My name is Thiti, I'm a Software Engineer.",
    "backlink": {
      "rect": "20:20:355:2540",
      "href": "https://webring.wonderful.software#thiti.dev"
    },
    "lastUpdated": "2023-04-26T10:01:25.451Z",
    "number": 45
  },
  "blog.kpping.me": {
    "url": "https://blog.kpping.me",
    "mobileImageUrlV2": "https://wonderfulsoftware.github.io/webring-site-screenshots/blog.kpping.me_375w@2x.png",
    "blurhash": "v4S6Su4o^*oz?FkBWYoItpf-t3M|?7RjNLt5D,NGjrWB$]WBE2ax9cNGobj[",
    "screenshotUpdatedAt": "2022-12-18T01:05:31.818Z",
    "description": "My simple micro blog.",
    "backlink": {
      "rect": "16:21:16:5214.65625",
      "href": "https://webring.wonderful.software#blog.kpping.me"
    },
    "lastUpdated": "2023-04-27T01:08:24.075Z",
    "number": 46
  },
  "myifew.com": {
    "url": "https://myifew.com",
    "mobileImageUrlV2": "https://wonderfulsoftware.github.io/webring-site-screenshots/myifew.com_375w@2x.png",
    "blurhash": "vJRC_F%LM|xs~pWYRiWE9Ft7jra#RPt7M|t6V[t7R%ay9Fj[t7ay_3a{WBWB",
    "screenshotUpdatedAt": "2023-04-27T01:08:32.720Z",
    "description": "Few Steps - ก้าวสั้นๆ แต่ไปเรื่อยๆ",
    "backlink": {
      "rect": "32:15:171.5:5439.75",
      "href": "https://webring.wonderful.software#myifew.com"
    },
    "lastUpdated": "2023-04-27T01:08:32.720Z",
    "number": 47
  },
  "jungai.me": {
    "url": "https://www.jungai.me",
    "mobileImageUrlV2": "https://wonderfulsoftware.github.io/webring-site-screenshots/jungai.me_375w@2x.png",
    "blurhash": "v0TSUA-;fQ-;%MfQfQfQfQfQfQfQ%MfQfQfQfQfQfQfQ%MfQfQfQfQfQfQfQ",
    "screenshotUpdatedAt": "2022-05-28T01:13:42.338Z",
    "description": null,
    "backlink": null,
    "lastUpdated": "2022-06-16T01:16:59.015Z"
  },
  "ntsd.dev": {
    "url": "https://ntsd.dev",
    "mobileImageUrlV2": "https://wonderfulsoftware.github.io/webring-site-screenshots/ntsd.dev_375w@2x.png",
    "blurhash": "v#JuDij[WBWC4nWBayof~qayofay%Mj[ofazofWBj[j[?bofWBay%MWBWBj[",
    "screenshotUpdatedAt": "2022-11-27T01:14:25.200Z",
    "description": "A full-stack software engineer.",
    "backlink": {
      "rect": null,
      "href": "https://webring.wonderful.software#ntsd.dev"
    },
    "lastUpdated": "2023-04-23T01:08:47.814Z"
  },
  "bellmcp.work": {
    "url": "https://bellmcp.work",
    "mobileImageUrlV2": "https://wonderfulsoftware.github.io/webring-site-screenshots/bellmcp.work_375w@2x.png",
    "blurhash": "vASigQ?b~q9GIUIo?bM{9F%MxuM{%MM{xua}%Lj@M{t7xuj[M{of%MWBIUt7",
    "screenshotUpdatedAt": "2022-12-28T01:07:11.487Z",
    "description": "Wutipat Khamnuansin, a computer science student, graphic designer, dreamer and many more.",
    "backlink": {
      "rect": "32:19:171.5:26345.75",
      "href": "https://webring.wonderful.software/#/bellmcp.work"
    },
    "lastUpdated": "2023-04-27T01:08:41.686Z",
    "number": 48
  },
  "jaruwat.fucking-thai.dev": {
    "url": "https://jaruwat.fucking-thai.dev",
    "mobileImageUrlV2": "https://wonderfulsoftware.github.io/webring-site-screenshots/jaruwat.fucking-thai.dev_375w@2x.png",
    "blurhash": "v2Rp8-_2bHt79F%MWCWB-;WXRjRj~WRkRiRj%MRkaej[M{Rit7xuE1Rit8t7",
    "screenshotUpdatedAt": "2021-10-15T17:29:35.127Z",
    "description": null,
    "backlink": null,
    "lastUpdated": "2021-10-15T17:29:35.127Z"
  },
  "khong.xyz": {
    "url": "https://khong.xyz",
    "mobileImageUrlV2": "https://wonderfulsoftware.github.io/webring-site-screenshots/khong.xyz_375w@2x.png",
    "blurhash": "v15qny~E0}9YNrM^r?af0JNC=F-D}I%4OrNF|}V}K5NZ32bn#SxJ0eWAxYs.",
    "screenshotUpdatedAt": "2023-04-27T01:09:33.038Z",
    "description": "A fullstack webdev with fiery passion to learn and innovate.",
    "backlink": {
      "rect": "66:66:154.5:5878.15625",
      "href": "https://webring.wonderful.software#khong.xyz"
    },
    "lastUpdated": "2023-04-27T01:09:33.038Z",
    "number": 50
  },
  "varkaria.tech": {
    "url": "https://varkaria.tech",
    "mobileImageUrlV2": "https://wonderfulsoftware.github.io/webring-site-screenshots/varkaria.tech_375w@2x.png",
    "blurhash": "v0TSUA-;fQ-;%MfQfQfQfQfQfQfQ%MfQfQfQfQfQfQfQ%MfQfQfQfQfQfQfQ",
    "screenshotUpdatedAt": "2022-06-25T01:18:19.943Z",
    "description": null,
    "backlink": null,
    "lastUpdated": "2022-12-13T01:15:37.112Z"
  },
  "krit.life": {
    "url": "https://krit.life",
    "mobileImageUrlV2": "https://wonderfulsoftware.github.io/webring-site-screenshots/krit.life_375w@2x.png",
    "blurhash": "v0TSUA-;fQ-;%MfQfQfQfQfQfQfQ%MfQfQfQfQfQfQfQ%MfQfQfQfQfQfQfQ",
    "screenshotUpdatedAt": "2022-10-28T01:37:46.344Z",
    "description": null,
    "backlink": null,
    "lastUpdated": "2022-12-13T01:15:40.366Z"
  },
  "engineerbudge.xyz": {
    "url": "http://www.engineerbudge.xyz",
    "mobileImageUrlV2": "https://wonderfulsoftware.github.io/webring-site-screenshots/engineerbudge.xyz_375w@2x.png",
    "blurhash": "vmI=P.nixuf5_4afofjuE0W=R*ogITf*ozofW9jYaeWBjEjZRjV@D%j[V@ax",
    "screenshotUpdatedAt": "2022-12-13T01:16:12.016Z",
    "description": null,
    "backlink": null,
    "lastUpdated": "2022-12-13T01:16:12.016Z"
  },
  "jaruwat.dev": {
    "url": "https://jaruwat.dev",
    "mobileImageUrlV2": "https://wonderfulsoftware.github.io/webring-site-screenshots/jaruwat.dev_375w@2x.png",
    "blurhash": "vA8Ef4IB0KxUMtxnR:N2VrS6s,oyR;Ro%1s+4m$|%MIq.AIvn#xn9DxptRM~",
    "screenshotUpdatedAt": "2023-04-10T01:06:11.209Z",
    "description": "I am Jaruwat Pohong, Desktop and Web Developer. (or just wanna be) Actually I am a student in Computer Science who would like to do anything about web design and frontend development. I usually play video games, listen to music and coding my mini project.",
    "backlink": {
      "rect": "32:32:333:10",
      "href": "https://webring.wonderful.software#jaruwat.dev"
    },
    "lastUpdated": "2023-04-27T01:08:57.092Z",
    "number": 49
  },
  "cwstory.com": {
    "url": "http://cwstory.com",
    "mobileImageUrlV2": "https://wonderfulsoftware.github.io/webring-site-screenshots/cwstory.com_375w@2x.png",
    "blurhash": "v8Sr},IU*0V@*0t7rCbbIARjS#V@%0RjE1WBKORQMJWUq[xuY6aeKOIUMJX7",
    "screenshotUpdatedAt": "2022-09-27T01:35:02.300Z",
    "description": "Programing 👨🏻‍💻 | Investment 💰 | Lifestyle 🏄🏻‍♂️ | Self-Improvement 🧘🏻.",
    "backlink": null,
    "lastUpdated": "2022-12-13T01:16:23.089Z"
  },
  "supavitk.com": {
    "url": "http://supavitk.com",
    "mobileImageUrlV2": "https://wonderfulsoftware.github.io/webring-site-screenshots/supavitk.com_375w@2x.png",
    "blurhash": "v2SY{q00%M?bxvRj9F-;_3-p9F%M-;_3D%s:00_2t7oLt7?bWBxu~q%2M{-;",
    "screenshotUpdatedAt": "2022-05-05T01:19:23.484Z",
    "description": "About me",
    "backlink": {
      "rect": "32:21:16:696.6875",
      "href": "https://webring.wonderful.software#supavitk.com"
    },
    "lastUpdated": "2023-04-27T01:09:57.863Z",
    "number": 52
  },
  "dmg.st": {
    "url": "https://dmg.st",
    "mobileImageUrlV2": "https://wonderfulsoftware.github.io/webring-site-screenshots/dmg.st_375w@2x.png",
    "blurhash": "vC63j6bGLwoMLcoLzsWVu-afTbofpvkBa1jFRjjGr^bat+fkRjjuZif7o}jZ",
    "screenshotUpdatedAt": "2023-03-30T01:11:34.494Z",
    "description": "DAMRONGSAK BULLETIN",
    "backlink": {
      "rect": "250:36:-40:70",
      "href": "https://webring.wonderful.software/#dmg.st"
    },
    "lastUpdated": "2023-04-27T01:10:12.544Z",
    "number": 53
  },
  "yume-dev.me": {
    "url": "https://yume-dev.me",
    "mobileImageUrlV2": "https://wonderfulsoftware.github.io/webring-site-screenshots/yume-dev.me_375w@2x.png",
    "blurhash": "v0TSUA-;fQ-;%MfQfQfQfQfQfQfQ%MfQfQfQfQfQfQfQ%MfQfQfQfQfQfQfQ",
    "screenshotUpdatedAt": "2022-05-24T01:25:03.365Z",
    "description": null,
    "backlink": null,
    "lastUpdated": "2023-02-05T01:17:42.930Z"
  },
  "ggolfz.me": {
    "url": "https://ggolfz.me",
    "mobileImageUrlV2": "https://wonderfulsoftware.github.io/webring-site-screenshots/ggolfz.me_375w@2x.png",
    "blurhash": "v.MQ*Jj[xuj[IUWBofay~qj[Rjj[-;WBayayIUj[j[j[xuayfQayM{j[j[j[",
    "screenshotUpdatedAt": "2023-04-26T00:57:02.602Z",
    "description": "GGolfz",
    "backlink": {
      "rect": "20:20:22.125:580",
      "href": "https://webring.wonderful.software#ggolfz.me"
    },
    "lastUpdated": "2023-04-27T00:59:20.694Z",
    "number": 8
  },
  "debuggingsoft.com": {
    "url": "https://debuggingsoft.com",
    "mobileImageUrlV2": "https://wonderfulsoftware.github.io/webring-site-screenshots/debuggingsoft.com_375w@2x.png",
    "blurhash": "v0TSUA-;fQ-;%MfQfQfQfQfQfQfQ%MfQfQfQfQfQfQfQ%MfQfQfQfQfQfQfQ",
    "screenshotUpdatedAt": "2023-04-27T01:10:33.129Z",
    "description": "มนุษย์เงินเดือนคนนึง ที่อยากแชร์ความรู้ และประสบการณ์การทำงานรวมถึงขายโปรแกรม เล็กๆน้อยๆ เพื่อสานต่อความฝันตั้งแต่เด็ก ^__^",
    "backlink": {
      "rect": null,
      "href": "https://webring.wonderful.software#naiwaen.debuggingsoft.com"
    },
    "lastUpdated": "2023-04-27T01:10:33.129Z",
    "number": 55
  },
  "natdanai.me": {
    "url": "https://natdanai.me",
    "mobileImageUrlV2": "https://wonderfulsoftware.github.io/webring-site-screenshots/natdanai.me_375w@2x.png",
    "blurhash": "voQ9fqf6.8aziuofo#ay?wj[M|aet-WBjFjZM|aynhj?t7WBROofxuWBWBog",
    "screenshotUpdatedAt": "2023-04-05T00:59:48.134Z",
    "description": "สมุดบันทึกเรื่องราวแต่ละช่วงเวลาของชีวิตไม่ว่าจะเป็น การทำงาน การเรียน การเดินทาง การท่องเที่ยว ผลงานการถ่ายภาพ ผลงานทำงาน โดยทุกอย่างจะถูกบันทึกไว้ในนี้",
    "backlink": {
      "rect": "20:17:177.5:8353.609375",
      "href": "https://webring.wonderful.software#natdanai.me"
    },
    "lastUpdated": "2023-04-27T01:10:47.570Z",
    "number": 56
  },
  "siriwatk.dev": {
    "url": "https://siriwatk.dev",
    "mobileImageUrlV2": "https://wonderfulsoftware.github.io/webring-site-screenshots/siriwatk.dev_375w@2x.png",
    "blurhash": "vtDU72kCM{a|.Tj[WBfQNGayt7j[IUf6t6ayWWj[jsayogj[WBj[jYa}azj[",
    "screenshotUpdatedAt": "2022-08-29T01:37:50.816Z",
    "description": "Welcome to my personal blog. This is where I share stuff from my discovery & experience.",
    "backlink": {
      "rect": "48:48:16:16",
      "href": "https://webring.wonderful.software#siriwatk.dev"
    },
    "lastUpdated": "2023-04-27T01:11:02.897Z",
    "number": 57
  },
  "anuwataravis.com": {
    "url": "https://anuwataravis.com",
    "mobileImageUrlV2": "https://wonderfulsoftware.github.io/webring-site-screenshots/anuwataravis.com_375w@2x.png",
    "blurhash": "vOD0Q2ofIUWB~qj[M{ay_3ayM{of_2ayM{j[-:ayRjj[xuayWBj[WBayazj[",
    "screenshotUpdatedAt": "2023-04-27T01:11:17.735Z",
    "description": "This domain may be for sale!",
    "backlink": null,
    "lastUpdated": "2023-04-27T01:11:17.735Z",
    "number": 58
  },
  "yothinix.com": {
    "url": "https://yothinix.com",
    "mobileImageUrlV2": "https://wonderfulsoftware.github.io/webring-site-screenshots/yothinix.com_375w@2x.png",
    "blurhash": "vPK_B=xuRkRj00t7Rjayx^IUWAof9GWBofa}ITt7WCRk~qt7a}j[xtRjj[jZ",
    "screenshotUpdatedAt": "2023-03-13T01:13:43.744Z",
    "description": "Banana is not apple, If you know what I mean 😏",
    "backlink": {
      "rect": null,
      "href": "https://webring.wonderful.software#yothinix.com"
    },
    "lastUpdated": "2023-04-27T01:11:29.570Z",
    "number": 59
  },
  "tech.duckfollow.co": {
    "url": "https://tech.duckfollow.co",
    "mobileImageUrlV2": "https://wonderfulsoftware.github.io/webring-site-screenshots/tech.duckfollow.co_375w@2x.png",
    "blurhash": "vB8gs#j?00j]MwoLxufP00oL~pj?xuj?RjoM^*j[9Gj@t9oLadax9GoJ?Gf8",
    "screenshotUpdatedAt": "2023-04-01T01:12:16.189Z",
    "description": "เทคโนโลยี อนิเมะ หนัง เรื่องราวน่าสนใจ",
    "backlink": {
      "rect": null,
      "href": "https://webring.wonderful.software#yothinix.com"
    },
    "lastUpdated": "2023-04-27T01:11:43.906Z",
    "number": 60
  },
  "nitpum.com": {
    "url": "https://nitpum.com",
    "mobileImageUrlV2": "https://wonderfulsoftware.github.io/webring-site-screenshots/nitpum.com_375w@2x.png",
    "blurhash": "vC7ws:o-M{$:r*NAbH%5%3oaofs:Ijn;t6bTXG%6t4NCIjxexWNXNFxbxYNG",
    "screenshotUpdatedAt": "2023-03-19T01:19:53.610Z",
    "description": "nitpum blog",
    "backlink": {
      "rect": "24:33:235.5:5532",
      "href": "https://webring.wonderful.software#nitpum.com"
    },
    "lastUpdated": "2023-04-27T01:11:53.926Z",
    "number": 61
  },
  "mesodiar.com": {
    "url": "https://mesodiar.com",
    "mobileImageUrlV2": "https://wonderfulsoftware.github.io/webring-site-screenshots/mesodiar.com_375w@2x.png",
    "blurhash": "vJRW0a8^oHx]-;ofRjjs~qyDWYRP9ZeooeWqDiMdV@tR$%bvRlV@.8x]RjM{",
    "screenshotUpdatedAt": "2023-04-26T01:10:32.685Z",
    "description": "Mils is a developer who is willing to learn technologies by summarizing into blogs with easy understanding and beginner-friendly. Her passion is helping people live better with technology through writing.",
    "backlink": {
      "rect": "80.96875:19:782.734375:147",
      "href": "https://webring.wonderful.software/#mesodiar.com"
    },
    "lastUpdated": "2023-04-27T01:12:05.852Z",
    "number": 62
  },
  "bigdatarpg.com": {
    "url": "https://bigdatarpg.com",
    "mobileImageUrlV2": "https://wonderfulsoftware.github.io/webring-site-screenshots/bigdatarpg.com_375w@2x.png",
    "blurhash": "vxJ9D$s*WDW?^|WYj[s,~LjZfPj[RjoIWCbIR:WrWCob9Jn~aybIt6bIWCoJ",
    "screenshotUpdatedAt": "2022-09-21T01:41:10.830Z",
    "description": "EXP = Learning + Doing",
    "backlink": {
      "rect": "94.359375:23:121.8125:147",
      "href": "https://webring.wonderful.software/"
    },
    "lastUpdated": "2023-04-27T01:12:16.981Z",
    "number": 63
  },
  "garden.narze.live": {
    "url": "https://garden.narze.live",
    "mobileImageUrlV2": "https://wonderfulsoftware.github.io/webring-site-screenshots/garden.narze.live_375w@2x.png",
    "blurhash": "v2S6Md00M{~q9GD*9F4o_NogD%ae^+%MaxIU-:^+?aM{?at7W;xu~q%2of%M",
    "screenshotUpdatedAt": "2023-03-15T01:01:28.642Z",
    "description": "My new digital garden, built with Obsidian & Quartz",
    "backlink": {
      "rect": "323.765625:44:18.75:758",
      "href": "https://webring.wonderful.software#garden.narze.live"
    },
    "lastUpdated": "2023-04-27T00:58:45.057Z",
    "number": 4
  },
  "janescience.com": {
    "url": "https://janescience.com",
    "mobileImageUrlV2": "https://wonderfulsoftware.github.io/webring-site-screenshots/janescience.com_375w@2x.png",
    "blurhash": "vSR3QN4Tt7%M~W-pM{NG%2xaWAR*4TD%t7xu?v%MWBRjS3ozozWBS2S4ofay",
    "screenshotUpdatedAt": "2023-03-19T01:24:44.331Z",
    "description": "ความรู้เกี่ยวกับ Programming ที่ผมได้ศึกษา สนใจ บันทึกไว้เป็นบทความ",
    "backlink": {
      "rect": "71.640625:40:287.359375:3595.4375",
      "href": "https://webring.wonderful.software#janescience.com"
    },
    "lastUpdated": "2023-04-27T01:17:04.799Z",
    "number": 85
  },
  "attomos.dev": {
    "url": "https://attomos.dev",
    "mobileImageUrlV2": "https://wonderfulsoftware.github.io/webring-site-screenshots/attomos.dev_375w@2x.png",
    "blurhash": "v2S6Sv00^}~p9D9FE4t8RiM|fm%MkGM|oa%L-,Rh9aM}D$D%ofxu00IU%L%L",
    "screenshotUpdatedAt": "2023-03-27T01:10:57.030Z",
    "description": null,
    "backlink": {
      "rect": "32:32:328.25:67",
      "href": "https://webring.wonderful.software#attomos.dev"
    },
    "lastUpdated": "2023-04-27T01:12:28.800Z",
    "number": 64
  },
  "edocstudio.info": {
    "url": "https://edocstudio.info",
    "mobileImageUrlV2": "https://wonderfulsoftware.github.io/webring-site-screenshots/edocstudio.info_375w@2x.png",
    "blurhash": "v0TSUA-;fQ-;%MfQfQfQfQfQfQfQ%MfQfQfQfQfQfQfQ%MfQfQfQfQfQfQfQ",
    "screenshotUpdatedAt": "2022-04-13T01:20:19.088Z",
    "description": "edoCstudio is a platform which you can share knowledge or idea to the World. Let join us !",
    "backlink": null,
    "lastUpdated": "2023-04-27T01:12:35.967Z",
    "number": 65
  },
  "microbenz.in.th": {
    "url": "https://microbenz.in.th",
    "mobileImageUrlV2": "https://wonderfulsoftware.github.io/webring-site-screenshots/microbenz.in.th_375w@2x.png",
    "blurhash": "vyM*5FRkxuj[kXs.jZazo#oLoJj[ofbIofjZ_NWCRjj[M{oeoeayRijubHfQ",
    "screenshotUpdatedAt": "2022-12-31T01:11:40.408Z",
    "description": "เบนซ์เขียนบล็อกนะจ๊ะ",
    "backlink": {
      "rect": "32:32:324.25:13.25",
      "href": "https://webring.wonderful.software#microbenz.in.th"
    },
    "lastUpdated": "2023-04-27T01:12:50.111Z",
    "number": 66
  },
  "nuttdam.com": {
    "url": "https://www.nuttdam.com",
    "mobileImageUrlV2": "https://wonderfulsoftware.github.io/webring-site-screenshots/nuttdam.com_375w@2x.png",
    "blurhash": "vYN,[4R*D%f600WAIUog%Moz%MWB~qae-;ay%2ofxtWBtRazRkof?bkCWBj[",
    "screenshotUpdatedAt": "2023-04-07T01:06:27.756Z",
    "description": "เนื่องจากแอปเปิลพึ่งเปิดตัว AIrPods Pro (รุ่นที่ 2) ไปเมื่อเดือนกันยายนที่ผ่านมา ผมที่ใช้ AirPods รุ่นที่ 2 อยู่ ก็เกิดอยากเสียเงินขึ้นมา ทำให้ได้กดสั่งซื้อ AirPods Pro ตัวใหม่นี้มาอย่างไม่ลังเล ทั้งๆ ที่ไม่เคยใช้ AirPods Pro มาก่อนเลย ด้วยเหตุผลก็คือ",
    "backlink": {
      "rect": "32:29:327:4.796875",
      "href": "https://webring.wonderful.software#nuttdam.com"
    },
    "lastUpdated": "2023-04-27T01:13:03.624Z",
    "number": 67
  },
  "blog.tawanchai.com": {
    "url": "https://blog.tawanchai.com",
    "mobileImageUrlV2": "https://wonderfulsoftware.github.io/webring-site-screenshots/blog.tawanchai.com_375w@2x.png",
    "blurhash": "vAAwVNxs4nj]4.ozxaj=00j^?bR%~WM_E0kD-qxtNFoJVFs;xuV@8{aexuo3",
    "screenshotUpdatedAt": "2022-05-29T07:09:41.909Z",
    "description": "The blog of tawanchai",
    "backlink": {
      "rect": "32:21:16:2161.90625",
      "href": "https://webring.wonderful.software#blog.tawanchai.com"
    },
    "lastUpdated": "2023-04-27T01:13:20.185Z",
    "number": 68
  },
  "utopiabeam.dev": {
    "url": "https://utopiabeam.dev",
    "mobileImageUrlV2": "https://wonderfulsoftware.github.io/webring-site-screenshots/utopiabeam.dev_375w@2x.png",
    "blurhash": "vEE{X{ogIoxt~qofkBa{00V@aKWC00t7t7M{-VkBtRjZi|%MtRRjIojbaLof",
    "screenshotUpdatedAt": "2023-01-08T01:20:24.895Z",
    "description": "Developer in a coconut shell",
    "backlink": {
      "rect": null,
      "href": "https://webring.wonderful.software#utopiabeam.dev"
    },
    "lastUpdated": "2023-04-27T01:13:36.345Z",
    "number": 69
  },
  "juver.xyz": {
    "url": "https://www.juver.xyz",
    "mobileImageUrlV2": "https://wonderfulsoftware.github.io/webring-site-screenshots/juver.xyz_375w@2x.png",
    "blurhash": "v0TSUA-;fQ-;%MfQfQfQfQfQfQfQ%MfQfQfQfQfQfQfQ%MfQfQfQfQfQfQfQ",
    "screenshotUpdatedAt": "2022-11-28T01:11:19.644Z",
    "description": null,
    "backlink": null,
    "lastUpdated": "2022-12-13T01:14:33.660Z"
  },
  "gusbell.tech": {
    "url": "https://gusbell.tech",
    "mobileImageUrlV2": "https://wonderfulsoftware.github.io/webring-site-screenshots/gusbell.tech_375w@2x.png",
    "blurhash": "v22=$EofD%WBRjj[t7ay9FWBxut7WBayoffQ~qofIUWBofj[WBay4nWB%Mof",
    "screenshotUpdatedAt": "2022-09-09T01:40:52.135Z",
    "description": "Gusbell's personal website & Menmory archive",
    "backlink": {
      "rect": "32:32:139.5:560",
      "href": "https://webring.wonderful.software#gusbell.tech"
    },
    "lastUpdated": "2023-04-27T01:13:41.524Z",
    "number": 70
  },
  "blog.nackie.party": {
    "url": "https://blog.nackie.party",
    "mobileImageUrlV2": "https://wonderfulsoftware.github.io/webring-site-screenshots/blog.nackie.party_375w@2x.png",
    "blurhash": "v968%FxBH=Oaemf,ozs88^kDx^sR.AskVrT1-QX9XUs7kCofoLjsO]skZ}S%",
    "screenshotUpdatedAt": "2023-03-05T01:27:46.973Z",
    "description": "Tumblr is a place to express yourself, discover yourself, and bond over the stuff you love. It's where your interests connect you with your people.",
    "backlink": null,
    "lastUpdated": "2023-04-27T01:13:52.954Z",
    "number": 71
  },
  "tinarskii.com": {
    "url": "https://www.tinarskii.com",
    "mobileImageUrlV2": "https://wonderfulsoftware.github.io/webring-site-screenshots/tinarskii.com_375w@2x.png",
    "blurhash": "v59G{;IX00$w4mMw_3kYtGI9xctS~ER.9ZnLNgt7xsXA4oo0%KtR$^x]D+I9",
    "screenshotUpdatedAt": "2023-04-27T01:14:10.804Z",
    "description": "I'm a student at Assumption Samutprakarn School. I love learning and teaching others. I enjoy math and science, but also love to code. I've been programming since I was 12 years old, and have been developing websites since then. I started contributing to open-source communities and have made some of",
    "backlink": {
      "rect": "32:32:56:64",
      "href": "https://webring.wonderful.software#tinarskii.com"
    },
    "lastUpdated": "2023-04-27T01:14:10.804Z",
    "number": 72
  },
  "blog.0002011.xyz": {
    "url": "https://blog.0002011.xyz",
    "mobileImageUrlV2": "https://wonderfulsoftware.github.io/webring-site-screenshots/blog.0002011.xyz_375w@2x.png",
    "blurhash": "vyM7fPR+IVt6_Nj[xaWC?boKofayxuayaffjIUofofayITayM|j[%LR+oej@",
    "screenshotUpdatedAt": "2022-11-23T01:22:04.672Z",
    "description": "thai northest developer blog",
    "backlink": {
      "rect": "32:32:232:139.71875",
      "href": "https://webring.wonderful.software#blog.0002011.xyz"
    },
    "lastUpdated": "2023-04-27T01:14:23.508Z",
    "number": 73
  },
  "katsuragi.detzz.in.th": {
    "url": "https://katsuragi.detzz.in.th/",
    "mobileImageUrlV2": "https://wonderfulsoftware.github.io/webring-site-screenshots/katsuragi.detzz.in.th_375w@2x.png",
    "blurhash": "v0TSUA-;fQ-;%MfQfQfQfQfQfQfQ%MfQfQfQfQfQfQfQ%MfQfQfQfQfQfQfQ",
    "screenshotUpdatedAt": "2023-01-13T01:20:14.626Z",
    "description": null,
    "backlink": null,
    "lastUpdated": "2023-04-07T01:07:54.916Z"
  },
  "patato.live": {
    "url": "https://patato.live",
    "mobileImageUrlV2": "https://wonderfulsoftware.github.io/webring-site-screenshots/patato.live_375w@2x.png",
    "blurhash": "vFA,nGob00W;nObE%3W=00Na~qbb?cI:IAf+?cNGIAW=IAWA-;bbxDoIs:bI",
    "screenshotUpdatedAt": "2023-02-24T01:19:20.811Z",
    "description": "who dis",
    "backlink": null,
    "lastUpdated": "2023-04-27T01:14:57.550Z",
    "number": 75
  },
  "mirailisc.me": {
    "url": "https://mirailisc.me",
    "mobileImageUrlV2": "https://wonderfulsoftware.github.io/webring-site-screenshots/mirailisc.me_375w@2x.png",
    "blurhash": "v1TI,aY7_2D4D4KkES8wHXPB0+8wQRKk9xD400O@?aDOMcOsR.H?ZgT09wIA",
    "screenshotUpdatedAt": "2023-04-27T01:15:11.150Z",
    "description": "Mirailisc's Portfolio website made by ReactTS",
    "backlink": {
      "rect": "32:32:65:24",
      "href": "https://webring.wonderful.software#mirailisc.me"
    },
    "lastUpdated": "2023-04-27T01:15:11.150Z",
    "number": 76
  },
  "th1nkk1d.xyz": {
    "url": "https://th1nkk1d.xyz",
    "mobileImageUrlV2": "https://wonderfulsoftware.github.io/webring-site-screenshots/th1nkk1d.xyz_375w@2x.png",
    "blurhash": "vKSPb2of~XWBNFj[xvWB?Hj[E1f6s;ayNFofx]WURPofXljsi_bHV[j[j?WV",
    "screenshotUpdatedAt": "2023-04-27T01:15:24.359Z",
    "description": "An indie developer and generalist enthusiasm who value a meaningful impact",
    "backlink": {
      "rect": "32:32:171.5:6029",
      "href": "https://webring.wonderful.software#th1nkk1d.xyz"
    },
    "lastUpdated": "2023-04-27T01:15:24.359Z",
    "number": 77
  },
  "karnwong.me": {
    "url": "https://karnwong.me",
    "mobileImageUrlV2": "https://wonderfulsoftware.github.io/webring-site-screenshots/karnwong.me_375w@2x.png",
    "blurhash": "v3R:HGM{?bxuayM{Rjj[~qM{9Fof00Ioxut74nRj%May_3RjIUoft7RjIUt7",
    "screenshotUpdatedAt": "2023-04-23T01:11:39.396Z",
    "description": "Homepage and blog by Karn Wong",
    "backlink": {
      "rect": "32:23:277.4375:435.5",
      "href": "https://webring.wonderful.software#karnwong.me"
    },
    "lastUpdated": "2023-04-27T01:08:09.864Z",
    "number": 44
  },
  "pawaret.dev": {
    "url": "https://pawaret.dev",
    "mobileImageUrlV2": "https://wonderfulsoftware.github.io/webring-site-screenshots/pawaret.dev_375w@2x.png",
    "blurhash": "v7AJp9xD00OF~Us.E2Nd00of^+WB0NW=^jxD59S4%0xZofS4RjxF-;WWWAn$",
    "screenshotUpdatedAt": "2023-02-21T01:20:36.800Z",
    "description": "Pawaret Muengkaew personal portfolio website made with 💖 using Next.js and Tailwind CSS",
    "backlink": {
      "rect": "32:32:303:41.5",
      "href": "https://webring.wonderful.software#pawaret.dev"
    },
    "lastUpdated": "2023-04-27T01:15:54.950Z",
    "number": 78
  },
  "supratouch.dev": {
    "url": "https://supratouch.dev"
  },
  "boonsong.dev": {
    "url": "https://boonsong.dev",
    "mobileImageUrlV2": "https://wonderfulsoftware.github.io/webring-site-screenshots/boonsong.dev_375w@2x.png",
    "blurhash": "v9SPU:9E%MxbD%IUWAxuIUM{WBt7MxV[R*k9t7t7kCWU^+xuWURk~q%MayRk",
    "screenshotUpdatedAt": "2023-01-23T01:15:21.465Z",
    "description": "A product developer and obsessed with coding. Nice to meet you all.",
    "backlink": {
      "rect": "32:32:116:16",
      "href": "https://webring.wonderful.software#boonsong.dev"
    },
    "lastUpdated": "2023-04-27T01:16:25.308Z",
    "number": 80
  },
  "lucian.solutions": {
    "url": "https://lucian.solutions",
    "mobileImageUrlV2": "https://wonderfulsoftware.github.io/webring-site-screenshots/lucian.solutions_375w@2x.png",
    "blurhash": "v9A9~KWA00ozV@flW;fP0ej[~CWBEMofslay^+ax9Zof-oayM|oLozoMxaRj",
    "screenshotUpdatedAt": "2023-01-28T01:19:31.442Z",
    "description": "Where art and algorithms meet. Art commissions including emotes, illustrations, and Live2D models.",
    "backlink": {
      "rect": "24:30:57.5:1107.5",
      "href": "https://webring.wonderful.software/#/lucian.solutions"
    },
    "lastUpdated": "2023-04-27T01:16:36.541Z",
    "number": 81
  },
  "poom.dev": {
    "url": "https://poom.dev",
    "mobileImageUrlV2": "https://wonderfulsoftware.github.io/webring-site-screenshots/poom.dev_375w@2x.png",
    "blurhash": "v3SidJ00~q%N.7xbRjx[-:%MM|Rjxv%MNFM{?I%MIUWEtMxvM|NEsroyouoN",
    "screenshotUpdatedAt": "2022-12-31T01:15:19.819Z",
    "description": "Phoomparin Mano is a software engineer based in Bangkok, Thailand.",
    "backlink": {
      "rect": "32:32:283:12",
      "href": "https://webring.wonderful.software#poom.dev"
    },
    "lastUpdated": "2023-04-27T01:16:42.433Z",
    "number": 82
  },
  "kajame.xyz": {
    "url": "https://kajame.xyz",
    "mobileImageUrlV2": "https://wonderfulsoftware.github.io/webring-site-screenshots/kajame.xyz_375w@2x.png",
    "blurhash": "vJS6V,WB%1j[~SfQNHj[IuofWAayIpayWBj[?DofbIfQ5Ft7xZay?8ofR.ay",
    "screenshotUpdatedAt": "2023-03-31T01:17:54.087Z",
    "description": "เว็บไซต์สำหรับรวมรวบบทความประสบการณ์การทำงานต่าง ๆ,เนื้อหาส่วนใหญ่จะเป็นเกี่ยวกับการเขียนโปรแกรมเน้อครับ,หากคุณผู้อ่านมีส่วนไหนที่สงสัย หรือติดปัญหา สามารถพิมพ์มาสอบถามได้ในช่องทางต่าง ๆ ในหน้า About ได้เลยนะครับ,ในอนาคตเดี๋ยวเจมส์เพิ่มช่องคอมเม้นท์ให้ในบทความนะครับ ตอนนี้ยังไม่มี ฮ่าาาา,หวังว่าบทคว",
    "backlink": {
      "rect": "32:32:243:20",
      "href": "https://webring.wonderful.software#kajame.xyz"
    },
    "lastUpdated": "2023-04-27T01:16:51.989Z",
    "number": 83
  },
  "0xchai.io": {
    "url": "https://0xchai.io",
    "mobileImageUrlV2": "https://wonderfulsoftware.github.io/webring-site-screenshots/0xchai.io_375w@2x.png",
    "blurhash": "v9SigRRj~qaz%1t7%Mj[?aRj9Fax_2of9Fj[IbayV?WVIUax%Mj[xUof%Nay",
    "screenshotUpdatedAt": "2023-01-03T06:43:25.306Z",
    "description": "I'm Software Dev from Thailand. I learn, practice and share Web2/ Web3 stuff",
    "backlink": {
      "rect": "32:34.3125:287:42.84375",
      "href": "https://webring.wonderful.software#0xchai.io"
    },
    "lastUpdated": "2023-04-27T01:16:58.513Z",
    "number": 84
  },
  "devahoy.com": {
    "url": "https://devahoy.com",
    "mobileImageUrlV2": "https://wonderfulsoftware.github.io/webring-site-screenshots/devahoy.com_375w@2x.png",
    "blurhash": "vDQ]]6a$~oWXtJWFD-WCEBWCs%a}kCWBD*oLIVaxofoe9Hoc-noJV:ocbKk9",
    "screenshotUpdatedAt": "2023-04-20T01:14:05.735Z",
    "description": "บล็อกเกี่ยวกับโปรแกรมมิ่ง, การเขียนโปรแกรม, Web Development และเรื่องอื่นๆ ที่สนใจ",
    "backlink": {
      "rect": "94:17:260:10019.5",
      "href": "https://webring.wonderful.software#devahoy.com"
    },
    "lastUpdated": "2023-04-26T01:15:29.959Z"
  },
  "thitikan.dev": {
    "url": "https://thitikan.dev",
    "mobileImageUrlV2": "https://wonderfulsoftware.github.io/webring-site-screenshots/thitikan.dev_375w@2x.png",
    "blurhash": "v0TSUA-;fQ-;%MfQfQfQfQfQfQfQ%MfQfQfQfQfQfQfQ%MfQfQfQfQfQfQfQ",
    "screenshotUpdatedAt": "2023-03-04T01:13:22.793Z",
    "description": null,
    "backlink": null,
    "lastUpdated": "2023-04-27T01:10:25.760Z",
    "number": 54
  },
  "taoisaman.com": {
    "url": "https://taoisaman.com",
    "mobileImageUrlV2": "https://wonderfulsoftware.github.io/webring-site-screenshots/taoisaman.com_375w@2x.png",
    "blurhash": "vbQvwRWB%Moy~qkBM{WBIUoft7ayIUWBofof?bj@RjWC9Fayxuoe?bj[M{ay",
    "screenshotUpdatedAt": "2023-04-05T01:06:15.446Z",
    "description": " เขียน blog ไปเรื่อยเน้นจดให้ตัวเองอ่าน และทุกคนได้อ่าน",
    "backlink": {
      "rect": "32:20:116.015625:6298",
      "href": "https://webring.wonderful.software#tao.isaman.com"
    },
    "lastUpdated": "2023-04-27T01:17:11.976Z",
    "number": 86
  },
  "khet.tech": {
    "url": "https://khet.tech",
    "mobileImageUrlV2": "https://wonderfulsoftware.github.io/webring-site-screenshots/khet.tech_375w@2x.png",
    "blurhash": "v37^=8Rk00Se9FofNGof00oJ~qjF_3bI-oWUM|WB-oW:J6s.ITxH_2ay4.WB",
    "screenshotUpdatedAt": "2023-04-25T01:17:07.282Z",
    "description": "Hi there, I'm Khet I'm a front-end developer with 3+ years of experience. Familiar with React (Hooks), MUI and I' m still keep learning new thing everyday!",
    "backlink": {
      "rect": "32:21:334:608",
      "href": "https://webring.wonderful.software/#/khet.tech"
    },
    "lastUpdated": "2023-04-27T01:17:28.869Z",
    "number": 87
  },
  "me.nsys.site": {
    "url": "https://me.nsys.site",
    "mobileImageUrlV2": "https://wonderfulsoftware.github.io/webring-site-screenshots/me.nsys.site_375w@2x.png",
    "blurhash": "v2R{+057-;^,01S~_1RS03x]?ZIV~Xo~IUV@~Woz9Zae$cIoR.-:Dgobo$sl",
    "screenshotUpdatedAt": "2023-04-07T05:27:13.443Z",
    "description": "หน้าแนะนำตัวของ nicenathapong",
    "backlink": {
      "rect": "32:32:232.5:4587",
      "href": "https://webring.wonderful.software#me.nsys.site"
    },
    "lastUpdated": "2023-04-27T01:17:40.124Z",
    "number": 88
  },
  "maythiwat.com": {
    "url": "https://maythiwat.com",
    "description": "Made possible by passion",
    "backlink": {
      "rect": "48:48:303:72",
      "href": "https://webring.wonderful.software#maythiwat.com"
    },
    "lastUpdated": "2023-04-27T01:17:56.673Z",
    "number": 89
  },
  "pusanstudio.com": {
    "url": "https://pusanstudio.com",
    "mobileImageUrlV2": "https://wonderfulsoftware.github.io/webring-site-screenshots/pusanstudio.com_375w@2x.png",
    "blurhash": "vFOziaw0~qt6^?X7.7oe0FwJD%ay_Lod9FWC0Ds9D%WC4_o0oyj[4pjZ%gof",
    "screenshotUpdatedAt": "2023-04-08T01:13:42.074Z",
    "description": "\"ความขี้เกียจ\" จะก่อให้เกิด \"สิ่งประดิษฐ์\" และ \"นวัตกรรม\"",
    "backlink": {
      "rect": "32:32:236.5:2082",
      "href": "https://webring.wonderful.software#pusanstudio.com"
    },
    "lastUpdated": "2023-04-27T01:18:06.213Z",
    "number": 90
  },
  "katsuragi.cyou": {
    "url": "https://katsuragi.cyou/",
    "mobileImageUrlV2": "https://wonderfulsoftware.github.io/webring-site-screenshots/katsuragi.cyou_375w@2x.png",
    "blurhash": "v497bL4TS{%4DhTaVst8OrDh?vM_Q.?wIAxu?vDikXafni%gIAogIpRP%MWA",
    "screenshotUpdatedAt": "2023-04-08T01:10:25.655Z",
    "description": "this is just my katsuragi.wav main page :D",
    "backlink": {
      "rect": "64:19:287:613",
      "href": "https://webring.wonderful.software#katsuragi.cyou"
    },
    "lastUpdated": "2023-04-27T01:14:39.821Z",
    "number": 74
  },
  "https://opecgame.in.th": {
    "url": "https://opecgame.in.th"
  },
  "opecgame.in.th": {
    "url": "https://opecgame.in.th"
  },
  "nayukikuu.xyz": {
    "url": "https://nayukikuu.xyz",
    "mobileImageUrlV2": "https://wonderfulsoftware.github.io/webring-site-screenshots/nayukikuu.xyz_375w@2x.png",
    "blurhash": "v36uxR^h00Dh8wXo-ntmJXVW%is7Mdb{xBkryGZ}tmi^jftmxBSit:ngXAaJ",
    "screenshotUpdatedAt": "2023-04-23T01:22:22.703Z",
    "description": "Nayuki's Personal Website",
    "backlink": {
      "rect": "45:46.265625:318:581.734375",
      "href": "https://webring.wonderful.software#nayukikuu.xyz"
    },
    "lastUpdated": "2023-04-23T01:22:22.703Z"
  },
  "me.kittichdevs.com": {
    "url": "http://me.kittichdevs.com/",
    "mobileImageUrlV2": "https://wonderfulsoftware.github.io/webring-site-screenshots/me.kittichdevs.com_375w@2x.png",
    "blurhash": "v59[Zp=w009bn5nkt7kC8wWF%jxCwwxajZbID4nl.AbF$*xGn*NHQksA%OR*",
    "screenshotUpdatedAt": "2023-04-27T01:18:48.156Z",
    "description": null,
    "backlink": {
      "rect": null,
      "href": "https://webring.wonderful.software#me.kittichdevs.com"
    },
    "lastUpdated": "2023-04-27T01:18:48.156Z",
    "number": 93
  },
  "yuttakhanb.dev": {
    "url": "https://www.yuttakhanb.dev/",
    "mobileImageUrlV2": "https://wonderfulsoftware.github.io/webring-site-screenshots/yuttakhanb.dev_375w@2x.png",
    "blurhash": "v34xxmo$Q.WAwOafbHbE4mR#x]bcB#XNrtaf^-oOM{ad]YnTSebr9?X3s;a#",
    "screenshotUpdatedAt": "2023-04-27T01:19:27.387Z",
    "description": null,
    "backlink": {
      "rect": "29.203125:29.203125:325.796875:20",
      "href": "https://webring.wonderful.software#yuttakhanb.dev"
    },
    "lastUpdated": "2023-04-27T01:19:27.387Z",
    "number": 94
  },
  "nayuki.cyou": {
    "url": "https://nayuki.cyou",
    "mobileImageUrlV2": "https://wonderfulsoftware.github.io/webring-site-screenshots/nayuki.cyou_375w@2x.png",
    "blurhash": "v36uxR^h00Dh8wXo-ntmJXVW%is7Mdb{xBkryGZ}tmi^jftmxBSit:ngXAaJ",
    "screenshotUpdatedAt": "2023-04-24T01:17:28.243Z",
    "description": "Nayuki's Personal Website",
    "backlink": {
      "rect": "45:46.265625:318:581.734375",
      "href": "https://webring.wonderful.software#nayukikuu.xyz"
    },
    "lastUpdated": "2023-04-27T01:18:27.247Z",
    "number": 92
  },
  "mistertfy64.com": {
    "url": "https://mistertfy64.com",
    "mobileImageUrlV2": "https://wonderfulsoftware.github.io/webring-site-screenshots/mistertfy64.com_375w@2x.png",
    "blurhash": "v8J*uB?b00~q00oMohM|00V_xaac00M_xuWA00M^%NNLRXRls,f5RVjKoMjE",
    "screenshotUpdatedAt": "2023-04-24T01:18:43.845Z",
    "description": "mistertfy64's personal website.",
    "backlink": {
      "rect": "16:19:18:552.265625",
      "href": "https://webring.wonderful.software#mistertfy64.com"
    },
    "lastUpdated": "2023-04-27T01:19:40.953Z",
    "number": 95
  }
}